syncedlyrics_aio/__init__.py
syncedlyrics_aio/__main__.py
syncedlyrics_aio/cli.py
syncedlyrics_aio/providers/__init__.py
syncedlyrics_aio/providers/base.py
syncedlyrics_aio/providers/deezer.py
syncedlyrics_aio/providers/genius.py
syncedlyrics_aio/providers/lrclib.py
syncedlyrics_aio/providers/lyricsify.py
syncedlyrics_aio/providers/megalobiz.py
syncedlyrics_aio/providers/musixmatch.py
syncedlyrics_aio/providers/netease.py
syncedlyrics_aio/providers/spotify.py
syncedlyrics_aio/providers/tencent.py
syncedlyrics_aio/utils.py
syncedlyrics_aio-1.0.2.dist-info/LICENSE
syncedlyrics_aio-1.0.2.dist-info/METADATA
syncedlyrics_aio-1.0.2.dist-info/WHEEL
syncedlyrics_aio-1.0.2.dist-info/entry_points.txt
syncedlyrics_aio-1.0.2.dist-info/RECORD
