Metadata-Version: 2.1
Name: syncedlyrics_aio
Version: 1.0.2
Summary: Get an LRC format (synchronized) lyrics for your music with aiohttp support
Home-page: https://github.com/rtcq/syncedlyrics
License: MIT
Author: Momo
Author-email: lo3me@proton.me
Requires-Python: >=3.8
Classifier: License :: OSI Approved :: MIT License
Classifier: Programming Language :: Python :: 3
Classifier: Programming Language :: Python :: 3.8
Classifier: Programming Language :: Python :: 3.9
Classifier: Programming Language :: Python :: 3.10
Classifier: Programming Language :: Python :: 3.11
Classifier: Programming Language :: Python :: 3.12
Classifier: Topic :: Multimedia :: Sound/Audio
Classifier: Topic :: Multimedia :: Sound/Audio :: Players
Classifier: Topic :: Multimedia :: Sound/Audio :: Speech
Requires-Dist: aiohttp (>=3.8.5,<4.0.0)
Requires-Dist: beautifulsoup4 (>=4.12.3,<5.0.0)
Requires-Dist: rapidfuzz (>=3.6.2,<4.0.0)
Project-URL: Bug Tracker, https://github.com/rtcq/syncedlyrics/issues
Project-URL: Repository, https://github.com/rtcq/syncedlyrics
